<?xml version="1.0" encoding="utf-8"?>
<Patch>
	<Operation Class="PatchOperationReplace">
		<success>Always</success>
		<xpath>Defs/ThingDef[defName="RM_GestaltEngine"]/designationCategory</xpath>
		<value>
			<designationCategory>Ferny_Mechanoids</designationCategory>
		</value>
	</Operation>
	<Operation Class="PatchOperationReplace">
		<success>Always</success>
		<xpath>Defs/ThingDef[defName="RM_VanometricGenerator"]/designationCategory</xpath>
		<value>
			<designationCategory>Ferny_PowerGeneration</designationCategory>
		</value>
	</Operation>

    <!-- RM_Turret_AutoShardLance -->
    <Operation Class="PatchOperationReplace">
        <xpath>Defs/ThingDef[defName="RM_Turret_AutoShardLance"]/designationCategory</xpath>
        <value>
            <designationCategory>Security</designationCategory>
        </value>
    </Operation>
    <!-- RM_Turret_AutoShardSwarmer -->
    <Operation Class="PatchOperationReplace">
        <xpath>Defs/ThingDef[defName="RM_Turret_AutoShardSwarmer"]/designationCategory</xpath>
        <value>
            <designationCategory>Security</designationCategory>
        </value>
    </Operation>
</Patch>
